json_updater/__init__.py
json_updater/main.py
json_updater/models.py
json_updater-0.0.6.dist-info/LICENSE
json_updater-0.0.6.dist-info/METADATA
json_updater-0.0.6.dist-info/WHEEL
json_updater-0.0.6.dist-info/top_level.txt
json_updater-0.0.6.dist-info/RECORD
