Metadata-Version: 2.1
Name: json-updater
Version: 0.0.6
Summary: Updates JSON according to a change spec
Home-page: https://github.com/FortressEngineering/json-updater
Author: Craig McConomy
Author-email: cmcconomy@fwig.com
Classifier: Programming Language :: Python :: 3
Classifier: Development Status :: 1 - Planning
Classifier: Operating System :: POSIX :: Linux
Requires-Python: >=3.9
License-File: LICENSE
Requires-Dist: jsonpath-ng (~=1.5.3)
Requires-Dist: dataclasses-json (~=0.5.7)
